odoo/addons/account_move_update_analytic/README.rst
odoo/addons/account_move_update_analytic/__init__.py
odoo/addons/account_move_update_analytic/__manifest__.py
odoo/addons/account_move_update_analytic/i18n/account_move_update_analytic.pot
odoo/addons/account_move_update_analytic/i18n/fr.po
odoo/addons/account_move_update_analytic/models/__init__.py
odoo/addons/account_move_update_analytic/models/account_move_line.py
odoo/addons/account_move_update_analytic/readme/CONTRIBUTORS.rst
odoo/addons/account_move_update_analytic/readme/DESCRIPTION.rst
odoo/addons/account_move_update_analytic/readme/USAGE.rst
odoo/addons/account_move_update_analytic/security/ir.model.access.csv
odoo/addons/account_move_update_analytic/static/description/icon.png
odoo/addons/account_move_update_analytic/static/description/index.html
odoo/addons/account_move_update_analytic/views/account_move_line_view.xml
odoo/addons/account_move_update_analytic/views/account_move_view.xml
odoo/addons/account_move_update_analytic/wizards/__init__.py
odoo/addons/account_move_update_analytic/wizards/account_move_update_analytic.py
odoo/addons/account_move_update_analytic/wizards/account_move_update_analytic_view.xml
odoo14_addon_account_move_update_analytic-14.0.1.0.1.dist-info/METADATA
odoo14_addon_account_move_update_analytic-14.0.1.0.1.dist-info/WHEEL
odoo14_addon_account_move_update_analytic-14.0.1.0.1.dist-info/top_level.txt
odoo14_addon_account_move_update_analytic-14.0.1.0.1.dist-info/RECORD
